pyrequirement/__init__.py
pyrequirement/main.py
pyrequirement-0.0.5.dist-info/LICENSE
pyrequirement-0.0.5.dist-info/METADATA
pyrequirement-0.0.5.dist-info/WHEEL
pyrequirement-0.0.5.dist-info/entry_points.txt
pyrequirement-0.0.5.dist-info/top_level.txt
pyrequirement-0.0.5.dist-info/RECORD
