Metadata-Version: 2.1
Name: pyrequirement
Version: 0.0.5
Summary: A simple tool to generate a requirements.txt from a pyproject.toml
Author-email: gothictomato <gothictomato@gothictomato.io>
Project-URL: Homepage, https://github.com/gothictomato/pyrequirement
Project-URL: Bug Tracker, https://github.com/gothictomato/pyrequirement/issues
Requires-Python: >=3.9
License-File: LICENSE
Requires-Dist: tomli
